gestion_banco_vega_canarejo/__init__.py
gestion_banco_vega_canarejo/cajeros.py
gestion_banco_vega_canarejo/clientes.py
gestion_banco_vega_canarejo/cuentas.py
gestion_banco_vega_canarejo/transacciones.py
gestion_banco_vega_canarejo-0.1.2.dist-info/licenses/LICENSE
gestion_banco_vega_canarejo-0.1.2.dist-info/METADATA
gestion_banco_vega_canarejo-0.1.2.dist-info/WHEEL
gestion_banco_vega_canarejo-0.1.2.dist-info/top_level.txt
gestion_banco_vega_canarejo-0.1.2.dist-info/RECORD
