Metadata-Version: 2.4
Name: gestion_banco_vega_canarejo
Version: 0.1.2
Summary: Paquete para gestión de operaciones bancarias básicas
Author: Alfonso Eduardo Vega Canarejo
Author-email: aovega.1b@gmail.com
Classifier: Programming Language :: Python :: 3
Classifier: License :: OSI Approved :: MIT License
Classifier: Operating System :: OS Independent
Requires-Python: >=3.6
License-File: LICENSE
Dynamic: author
Dynamic: author-email
Dynamic: classifier
Dynamic: description
Dynamic: description-content-type
Dynamic: license-file
Dynamic: requires-python
Dynamic: summary
